makesimple/__init__.py
makesimple/_version.py
makesimple/makesimple.py
makesimple-0.1.0.dist-info/METADATA
makesimple-0.1.0.dist-info/WHEEL
makesimple-0.1.0.dist-info/RECORD
