Metadata-Version: 2.1
Name: makesimple
Version: 0.1.0
Summary: MakeSimple simplifies Make/CMake commands for easy use in Python scripts.
Home-page: https://github.com/Hom-Wang/makesimple
License: MIT
Author: kris.wang
Author-email: wenhom.wang@gmail.com
Requires-Python: >=3.10,<4.0
Classifier: License :: OSI Approved :: MIT License
Classifier: Programming Language :: Python :: 3
Classifier: Programming Language :: Python :: 3.10
Classifier: Programming Language :: Python :: 3.11
Classifier: Programming Language :: Python :: 3.12
Classifier: Programming Language :: Python :: 3.13
Project-URL: Repository, https://github.com/Hom-Wang/makesimple
